komodoml/__init__.py
komodoml/base/__init__.py
komodoml/base/base_model.py
komodoml/base/wrapper.py
komodoml/models/__init__.py
komodoml/models/decision_tree.py
komodoml/resampling/__init__.py
komodoml/resampling/base.py
komodoml/resampling/bootstrap.py
komodoml/resampling/kfold.py
komodoml-0.0.0.dist-info/licenses/LICENSE
komodoml-0.0.0.dist-info/METADATA
komodoml-0.0.0.dist-info/WHEEL
komodoml-0.0.0.dist-info/top_level.txt
komodoml-0.0.0.dist-info/RECORD
