Metadata-Version: 2.4
Name: komodoml
Version: 0.0.0
Summary: A unified ML toolkit for models, metrics, plotting, and interpretability.
Author-email: Yeray Martínez <yeraym12@gmail.com>
License:                                  Apache License
Project-URL: Homepage, https://github.com/yermarti/komodoml
Project-URL: Documentation, https://yermarti.github.io/komodoml
Project-URL: Repository, https://github.com/yermarti/komodoml
Project-URL: Issues, https://github.com/yermarti/komodoml/issues
Keywords: machine-learning,ml,toolkit,metrics,interpretability
Requires-Python: >=3.8
License-File: LICENSE
Requires-Dist: scikit-learn>=1.0.0
Requires-Dist: scipy>=1.7.0
Requires-Dist: numpy>=1.20.0
Dynamic: license-file
